<?xml version="1.0" encoding="UTF-8"?>
<group name="dragnet,supply_chain">
  <!-- Dragnet [Container]: dragnet-container-2026-2898 — Vulnerable Base Image Pull | Status: deprecated | Sigma ID: 365a1ba2-d90f-5c45-b15a-c6bb084768cf -->
  <rule id="676442" level="10">
    <description>Dragnet [Container]: dragnet-container-2026-2898 — Vulnerable Base Image Pull</description>
    <field name="process.name" type="pcre2">ubuntu:12\.04|ubuntu:12\.10</field>
    <mitre>
      <id>T1610</id>
      <id>T1611</id>
    </mitre>
  </rule>
</group>