<?xml version="1.0" encoding="UTF-8"?>
<group name="dragnet,supply_chain">
  <!-- Dragnet [Container]: dragnet-container-2024-0362 — Vulnerable Base Image Pull | Status: deprecated | Sigma ID: 0c064c49-964c-5686-b18d-dfb9d1b4e6e0 -->
  <rule id="230364" level="12">
    <description>Dragnet [Container]: dragnet-container-2024-0362 — Vulnerable Base Image Pull</description>
    <field name="process.name" type="pcre2">oraclelinux:6|oraclelinux:7|ubuntu:14\.04|ubuntu:14\.04-ESM|ubuntu:16\.04|ubuntu:16\.04-ESM</field>
    <mitre>
      <id>T1610</id>
      <id>T1611</id>
    </mitre>
  </rule>
</group>